webai_element_sdk/__init__.py
webai_element_sdk/__main__.py
webai_element_sdk/comms/__init__.py
webai_element_sdk/comms/agent.py
webai_element_sdk/comms/messages.py
webai_element_sdk/comms/utils.py
webai_element_sdk/element/__init__.py
webai_element_sdk/element/context.py
webai_element_sdk/element/element.py
webai_element_sdk/element/settings.py
webai_element_sdk/element/utils.py
webai_element_sdk/element/variables.py
webai_element_sdk/runner/__init__.py
webai_element_sdk/runner/agent_comms.py
webai_element_sdk/runner/element_client.py
webai_element_sdk/runner/element_server.py
webai_element_sdk-0.9.12.dist-info/METADATA
webai_element_sdk-0.9.12.dist-info/WHEEL
webai_element_sdk-0.9.12.dist-info/top_level.txt
webai_element_sdk-0.9.12.dist-info/RECORD
