Metadata-Version: 2.1
Name: webai_element_sdk
Version: 0.9.12
Summary: The official WebAI Element SDK.
Classifier: Programming Language :: Rust
Classifier: Programming Language :: Python :: Implementation :: CPython
Classifier: Programming Language :: Python :: Implementation :: PyPy
Classifier: License :: OSI Approved :: GNU General Public License v3 (GPLv3)
Requires-Python: >=3.10
Requires-Dist: numpy>=1.23.5
Requires-Dist: Brotli==1.1.0
Requires-Dist: msgspec==0.18.5
Requires-Dist: click==8.1.7
Requires-Dist: semver==3.0.2
Requires-Dist: typing-extensions==4.12.2
Requires-Dist: aiohttp==3.10.10
Provides-Extra: tests
Requires-Dist: pytest==7.4.3; extra == "tests"
Requires-Dist: pytest-asyncio==0.21.1; extra == "tests"
Requires-Dist: pytest-cov==4.1.0; extra == "tests"
Provides-Extra: docs
Requires-Dist: mkdocs==1.6.0; extra == "docs"
Requires-Dist: mkdocs-material==9.5.21; extra == "docs"
Requires-Dist: mkdocstrings==0.25.0; extra == "docs"
Requires-Dist: mkdocstrings-python==1.10.8; extra == "docs"
Requires-Dist: mkdocs-gen-files==0.5.0; extra == "docs"
